{
  "type": "bubble",
  "styles": {
    "footer": {
      "separator": true
    }
  },
  "body": {
    "type": "box",
    "layout": "vertical",
    "contents": [
      {
        "type": "text",
        "text": "{{ data.goal_status }}",
        "weight": "bold",
        "color": "{{ data.goal_color }}",
        "size": "sm"
      },
      {
        "type": "text",
        "text": "Sales Report",
        "weight": "bold",
        "size": "xl",
        "margin": "md"
      },
      {
        "type": "text",
        "text": "G-Zone銀座ラ・ボエム",
        "size": "xs",
        "color": "#aaaaaa",
        
        "wrap": true
      },
      {
        "type": "text",
        "text": "{{ data.dates }}",
        "size": "xs",
        "color": "#aaaaaa",
        "margin": "md",
        "wrap": true
      },
      {
        "type": "separator",
        "margin": "xxl"
      },
      {
        "type": "box",
        "layout": "vertical",
        "margin": "xxl",
        "spacing": "sm",
        "contents": [
          {
            "type": "box",
            "layout": "horizontal",
            "contents": [
              {
                "type": "text",
                "text": "Last Year Sales",
                "size": "sm",
                "color": "#555555",
                "flex": 0
              },
              {
                "type": "text",
                "text": "{{ data.last_year }}",
                "size": "sm",
                "color": "#111111",
                "align": "end"
              }
            ]
          },
          {
            "type": "box",
            "layout": "horizontal",
            "contents": [
              {
                "type": "text",
                "text": "Goal",
                "size": "sm",
                "color": "#555555",
                "flex": 0
              },
              {
                "type": "text",
                "text": "{{ data.goal }}",
                "size": "sm",
                "color": "#111111",
                "align": "end"
              }
            ]
          },
          {
            "type": "box",
            "layout": "horizontal",
            "contents": [
              {
                "type": "text",
                "text": "> Sales",
                "weight": "bold",
                "size": "md",
                "margin": "sm",
                "color": "#555555",
                "flex": 0
              },
              {
                "type": "text",
                "text": "{{ data.saless }}",
                "size": "md",
                "margin": "sm",
                "weight": "bold",
                "color": "#111111",
                "align": "end"
              }
            ]
          }
        ]
      },
      {
        "type": "separator",
        "margin": "xxl"
      },
      {
        "type": "box",
        "layout": "vertical",
        "margin": "xxl",
        "spacing": "sm",
        "contents": [
          {
            "type": "box",
            "layout": "horizontal",
            "contents": [
              {
                "type": "text",
                "text": "3 PM",
                "size": "sm",
                "color": "#555555",
                "flex": 0
              },
              {
                "type": "text",
                "text": "{{ data.sanji }}",
                "size": "sm",
                "color": "#111111",
                "align": "end"
              }
            ]
          },
          {
            "type": "box",
            "layout": "horizontal",
            "contents": [
              {
                "type": "text",
                "text": "6 PM",
                "size": "sm",
                "color": "#555555",
                "flex": 0
              },
              {
                "type": "text",
                "text": "{{ data.rokuji }}",
                "size": "sm",
                "color": "#111111",
                "align": "end"
              }
            ]
          },
          {
            "type": "box",
            "layout": "horizontal",
            "contents": [
              {
                "type": "text",
                "text": "9 PM",
                "size": "sm",
                "color": "#555555",
                "flex": 0
              },
              {
                "type": "text",
                "text": "{{ data.kuji }}",
                "size": "sm",
                "color": "#111111",
                "align": "end"
              }
            ]
          }
        ]
      },
      {
        "type": "separator",
        "margin": "xxl"
      },
      {
        "type": "box",
        "layout": "vertical",
        "margin": "xxl",
        "spacing": "sm",
        "contents": [
          {
            "type": "box",
            "layout": "horizontal",
            "contents": [
              {
                "type": "text",
                "text": "Change from last year",
                "weight": "bold",
                "size": "sm",
                "color": "#555555",
                "flex": 0
              },
              {
                "type": "text",
                "text": "{{ data.changes }}",
                "size": "sm",
                "color": "#111111",
                "align": "end"
              }
            ]
          }
        ]
      },
      {
        "type": "separator",
        "margin": "xxl"
      },
      {
        "type": "box",
        "layout": "vertical",
        "margin": "xxl",
        "spacing": "sm",
        "contents": [
          {
            "type": "box",
            "layout": "horizontal",
            "contents": [
              {
                "type": "text",
                "text": "Monthly Goal",
                "weight": "bold",
                "size": "sm",
                "color": "#aaaaaa",
                "flex": 0
              },
              {
                "type": "text",
                "text": "{{ data.monthly_goal }}",
                "weight": "bold",
                "size": "sm",
                "color": "#aaaaaa",
                "align": "end"
              }
            ]
          },
          {
            "type": "box",
            "layout": "horizontal",
            "contents": [
              {
                "type": "text",
                "text": "Current Monthly Sales",
              
                "size": "sm",
                "color": "#555555",
                "flex": 0
              },
              {
                "type": "text",
                "text": "{{ data.currents }}",
                "weight": "bold",
                "size": "sm",
                "color": "#111111",
                "align": "end"
              }
            ]
          }
        ]
      },
      {
        "type": "separator",
        "margin": "xxl"
      },
      {
        "type": "box",
        "layout": "vertical",
        "margin": "xxl",
        "spacing": "sm",
        "contents": [
          {
            "type": "box",
            "layout": "horizontal",
            "contents": [
              {
                "type": "text",
                "text": "Amount Left",
               
                "size": "sm",
                "color": "#111111",
                "flex": 0
              },
              {
                "type": "text",
                "text": "{{ data.lefts }}",
                "weight": "bold",
                "size": "sm",
                "color": "#111111",
                "align": "end"
              }
            ]
          },
          {
            "type": "box",
            "layout": "horizontal",
            "contents": [
              {
                "type": "text",
                "text": "Progress",
              
                "size": "sm",
                "color": "#555555",
                "flex": 0
              },
              {
                "type": "text",
                "text": "{{ data.progress }}",
                "weight": "bold",
                "size": "sm",
                "color": "#111111",
                "align": "end"
              }
            ]
          }
        ]
      }
    ]
  }
}